{
  "apiVersion": 1,
  "groups": [
    {
      "folder": "",
      "interval": "1m",
      "name": "disk-space",
      "orgId": 1,
      "rules": [
        {
          "annotations": {
            "description": "Disk on {{ $labels.bhost }} at {{ $labels.mountpoint }} is {{ printf \"%.1f\" $values.B.Value }}% used (pool-limited free space).",
            "summary": "{{ if $labels.guest }}{{ $labels.guest }} ({{ $labels.bhost }}) {{ $labels.guest_mountpoint }}{{ else }}{{ $labels.bhost }} {{ $labels.mountpoint }}{{ end }} \u2014 {{ printf \"%.1f\" $values.B.Value }}% full"
          },
          "condition": "C",
          "data": [
            {
              "datasourceUid": "P4169E866C3094E38",
              "model": {
                "datasource": {
                  "type": "victoriametrics-metrics-datasource",
                  "uid": "P4169E866C3094E38"
                },
                "editorMode": "code",
                "expr": "(100 * (1 - node_filesystem_avail_bytes{mountpoint=~\"/rpool/data/subvol.*\"} / node_filesystem_size_bytes{mountpoint=~\"/rpool/data/subvol.*\"}) * on(bhost,mountpoint) group_left(guest,guest_mountpoint) pve_lxc_volume_info) or (100 * (1 - node_filesystem_avail_bytes{bhost=~\"raum|valak|bael\",mountpoint!~\"/rpool/data/subvol.*\",fstype=\"zfs\"} / node_filesystem_size_bytes{bhost=~\"raum|valak|bael\",mountpoint!~\"/rpool/data/subvol.*\",fstype=\"zfs\"}))",
                "instant": false,
                "intervalMs": 60000,
                "maxDataPoints": 43200,
                "range": true,
                "refId": "A"
              },
              "refId": "A",
              "relativeTimeRange": {
                "from": 300,
                "to": 0
              }
            },
            {
              "datasourceUid": "__expr__",
              "model": {
                "datasource": {
                  "type": "__expr__",
                  "uid": "__expr__"
                },
                "expression": "A",
                "intervalMs": 1000,
                "maxDataPoints": 43200,
                "reducer": "last",
                "refId": "B",
                "type": "reduce"
              },
              "refId": "B",
              "relativeTimeRange": {
                "from": 300,
                "to": 0
              }
            },
            {
              "datasourceUid": "__expr__",
              "model": {
                "conditions": [
                  {
                    "evaluator": {
                      "params": [
                        90
                      ],
                      "type": "gt"
                    },
                    "operator": {
                      "type": "and"
                    },
                    "query": {
                      "params": [
                        "B"
                      ]
                    },
                    "reducer": {
                      "type": "last"
                    },
                    "type": "query"
                  }
                ],
                "datasource": {
                  "type": "__expr__",
                  "uid": "__expr__"
                },
                "expression": "B",
                "intervalMs": 1000,
                "maxDataPoints": 43200,
                "refId": "C",
                "type": "threshold"
              },
              "refId": "C",
              "relativeTimeRange": {
                "from": 300,
                "to": 0
              }
            }
          ],
          "execErrState": "Error",
          "for": "5m",
          "isPaused": false,
          "labels": {
            "severity": "warning"
          },
          "noDataState": "OK",
          "title": "Disk volumes \u2265 90% full",
          "uid": "cfrooj2f2rbb4c"
        }
      ]
    }
  ]
}
